sfconn/__init__.py
sfconn/conn.py
sfconn/cursor.py
sfconn/jwt.py
sfconn/privkey.py
sfconn/py.typed
sfconn/utils.py
sfconn/utils_snowpark.py
sfconn-0.3.3.dist-info/METADATA
sfconn-0.3.3.dist-info/WHEEL
sfconn-0.3.3.dist-info/top_level.txt
sfconn-0.3.3.dist-info/RECORD
