Metadata-Version: 2.1
Name: sfconn
Version: 0.3.3
Summary: Snowflake connection helper functions
Author-email: Paresh Adhia <padhia+github@gmail.com>
Project-URL: Homepage, https://github.com/padhia/sfconn
Classifier: Programming Language :: Python :: 3
Requires-Python: >=3.11
Requires-Dist: snowflake-connector-python[secure-local-storage]>=3.7.0
Requires-Dist: pyjwt
Provides-Extra: snowpark
Requires-Dist: snowflake-snowpark-python; extra == "snowpark"
Provides-Extra: test
Requires-Dist: pytest; extra == "test"
